{
  "incident_id": "INCIDENT-1761130853",
  "shutdown_reason": "threshold_violation",
  "shutdown_timestamp": 1761130853.5363863,
  "shutdown_timestamp_iso": "2025-10-22T08:00:53.536386",
  "violations": [
    {
      "violation_id": "critical",
      "violation_type": "arousal_runaway",
      "legacy_violation_type": "arousal_sustained_high",
      "threat_level": "critical",
      "severity": "emergency",
      "timestamp": 1761130853.5347884,
      "timestamp_iso": "2025-10-22T08:00:53.534788",
      "description": "Safety violation recorded",
      "metrics": {},
      "source_component": "consciousness-safety",
      "automatic_action_taken": null,
      "message": "Safety violation recorded"
    }
  ],
  "system_state_snapshot": {
    "timestamp": 1761130853.5379124,
    "timestamp_iso": "2025-10-22T08:00:53.537918",
    "pid": 20254,
    "tig_nodes": 